opt_einsum/__init__.py
opt_einsum/_version.py
opt_einsum/blas.py
opt_einsum/contract.py
opt_einsum/helpers.py
opt_einsum/parser.py
opt_einsum/path_random.py
opt_einsum/paths.py
opt_einsum/sharing.py
opt_einsum/backends/__init__.py
opt_einsum/backends/cupy.py
opt_einsum/backends/dispatch.py
opt_einsum/backends/jax.py
opt_einsum/backends/tensorflow.py
opt_einsum/backends/theano.py
opt_einsum/backends/torch.py
opt_einsum/tests/__init__.py
opt_einsum/tests/test_backends.py
opt_einsum/tests/test_blas.py
opt_einsum/tests/test_contract.py
opt_einsum/tests/test_edge_cases.py
opt_einsum/tests/test_input.py
opt_einsum/tests/test_paths.py
opt_einsum/tests/test_sharing.py
opt_einsum-3.2.1.dist-info/LICENSE
opt_einsum-3.2.1.dist-info/METADATA
opt_einsum-3.2.1.dist-info/WHEEL
opt_einsum-3.2.1.dist-info/top_level.txt
opt_einsum-3.2.1.dist-info/zip-safe
opt_einsum-3.2.1.dist-info/RECORD
