Metadata-Version: 2.1
Name: opt-einsum
Version: 3.2.1
Summary: Optimizing numpys einsum function
Home-page: https://github.com/dgasmith/opt_einsum
Author: Daniel Smith
Author-email: dgasmith@icloud.com
License: MIT
Platform: UNKNOWN
Classifier: Development Status :: 5 - Production/Stable
Classifier: Intended Audience :: Science/Research
Classifier: Intended Audience :: Developers
Classifier: License :: OSI Approved
Classifier: Programming Language :: Python
Classifier: Programming Language :: Python :: 3
Classifier: Programming Language :: Python :: 3.5
Classifier: Programming Language :: Python :: 3.6
Classifier: Programming Language :: Python :: 3.7
Classifier: Programming Language :: Python :: 3.8
Requires-Python: >=3.5
Provides-Extra: docs
Provides-Extra: tests
